{
  "@metadata": {
    "authors": [
      "r.hofmann@sap.com"
    ],
    "last-modified": "2016-12-20",
    "version": "0.1.0"
  },
  "blocked": [
    {
      "id": "KP",
      "name": "North Korea",
      "comment": "Access blocked due to export control policies"
    },
    {
      "id": "SY",
      "country": "Syria",
      "comment": "Access blocked due to export control policies",
      "active-from": "2017-01-01"
    },
    {
      "id": "IR",
      "country": "Iran",
      "comment": "Access blocked due to export control policies",
      "active-from": "2017-01-01"
    },
    {
      "id": "UA",
      "country": "Ukraine",
      "comment": "Access blocked due to export control policies",
      "active-from": "2017-01-01"
    },
    {
      "id": "SD",
      "country": "Sudan",
      "comment": "Access blocked due to export control policies",
      "active-from": "2017-01-01"
    },
    {
      "id": "CU",
      "country": "Cuba",
      "comment": "Access blocked due to export control policies",
      "active-from": "2017-01-01",
      "active-till": "2017-12-31"
    }
  ]
}
